x_to_nwb/ABF1Converter.py
x_to_nwb/ABF2Converter.py
x_to_nwb/DatConverter.py
x_to_nwb/__init__.py
x_to_nwb/_version.py
x_to_nwb/conversion.py
x_to_nwb/conversion_utils.py
x_to_nwb/hr_bundle.py
x_to_nwb/hr_nodes.py
x_to_nwb/hr_segments.py
x_to_nwb/hr_stimsetgenerator.py
x_to_nwb/hr_struct.py
x_to_nwb/hr_treenode.py
x_to_nwb-0.2.2.dist-info/LICENSE
x_to_nwb-0.2.2.dist-info/METADATA
x_to_nwb-0.2.2.dist-info/WHEEL
x_to_nwb-0.2.2.dist-info/entry_points.txt
x_to_nwb-0.2.2.dist-info/top_level.txt
x_to_nwb-0.2.2.dist-info/RECORD
