Metadata-Version: 2.1
Name: x-to-nwb
Version: 0.2.2
Summary: Convert various patch-clamp data formats to NWBv2
Home-page: https://github.com/byte-physics/x-to-nwb
Author: Thomas Braun
Author-email: packages@byte-physics.de
License: UNKNOWN
Platform: UNKNOWN
Classifier: Development Status :: 5 - Production/Stable
Classifier: Environment :: Console
Classifier: Intended Audience :: Science/Research
Classifier: License :: Free To Use But Restricted
Classifier: Operating System :: OS Independent
Classifier: Programming Language :: Python :: 3.6
Classifier: Programming Language :: Python :: 3.7
Classifier: Programming Language :: Python :: 3.8
Classifier: Topic :: Scientific/Engineering
Requires-Python: >=3.6
Requires-Dist: pynwb (<2.0.0,>=1.3.2)
Requires-Dist: h5py (<3,>=2.10.0)
Requires-Dist: flake8 (>=3.8.4)
Requires-Dist: black (>=20.8b1)
Requires-Dist: versioneer (>=0.19)
Requires-Dist: twine (>=3.2.0)
Requires-Dist: pytest (>=6.1.2)
Requires-Dist: pytest-xdist (>=2.1.0)
Requires-Dist: pyabf (>=2.2.8)
